Workbook

Sheet Ads
A1: ad_id | B1: brand | C1: ring | D1: channel | E1: date_first_seen | F1: date_last_seen | G1: format | H1: duration_sec | I1: language | J1: product_line | K1: claim_primary | L1: claim_secondary | M1: register | N1: proof_device | O1: cta_channel | P1: audience_signal | Q1: addresses_objection | R1: variant_count | S1: views | T1: source_url | U1: coder | V1: notes
A2: =IF(B2="","",ROW()-1) | B2: State Life Insurance Corporation of Pakistan | C2: =IFERROR(VLOOKUP(B2,Brands!$A:$B,2,FALSE),"") | D2: meta | F2: 2026-08-27 | G2: static | I2: mixed | J2: brand_corporate | K2: faith_compliance | L2: other | M2: reassurance | N2: none | O2: none | P2: mass | Q2: no | R2: 1 | T2: https://www.instagram.com/statelifeofficialpakistan/p/Dcd2vnBE2WW/ | U2: claude | V2: Eid Milad-un-Nabi greeting. [img: media/statelifeofficialpakistan/Dcd2vnBE2WW.jpg]
A3: =IF(B3="","",ROW()-1) | B3: State Life Insurance Corporation of Pakistan | C3: =IFERROR(VLOOKUP(B3,Brands!$A:$B,2,FALSE),"") | D3: meta | F3: 2026-08-27 | G3: static | I3: mixed | J3: brand_corporate | K3: brand_corporate | L3: other | M3: pride | N3: none | O3: none | P3: youth | Q3: no | R3: 1 | T3: https://www.instagram.com/statelifeofficialpakistan/p/DcdSRaYDJgx/ | U3: claude | V3: Qimam Fellowship students at Principal Office. Institutional PR. [img: media/statelifeofficialpakistan/DcdSRaYDJgx.jpg]
A4: =IF(B4="","",ROW()-1) | B4: State Life Insurance Corporation of Pakistan | C4: =IFERROR(VLOOKUP(B4,Brands!$A:$B,2,FALSE),"") | D4: meta | F4: 2026-08-27 | G4: static | I4: mixed | J4: brand_corporate | K4: brand_corporate | L4: other | M4: pride | N4: none | O4: none | P4: sme_corporate | Q4: no | R4: 1 | T4: https://www.instagram.com/statelifeofficialpakistan/p/DcK3NfajCKE/ | U4: claude | V4: Divisional Head at infrastructure conference. Grip-and-grin. [img: media/statelifeofficialpakistan/DcK3NfajCKE.jpg]
A5: =IF(B5="","",ROW()-1) | B5: State Life Insurance Corporation of Pakistan | C5: =IFERROR(VLOOKUP(B5,Brands!$A:$B,2,FALSE),"") | D5: meta | F5: 2026-08-27 | G5: static | I5: mixed | J5: brand_corporate | K5: national_trust | L5: other | M5: pride | N5: none | O5: none | P5: mass | Q5: no | R5: 1 | T5: https://www.instagram.com/statelifeofficialpakistan/p/DcByD4DDwQZ/ | U5: claude | V5: Flag-raising event photo. [img: media/statelifeofficialpakistan/DcByD4DDwQZ.jpg]
A6: =IF(B6="","",ROW()-1) | B6: State Life Insurance Corporation of Pakistan | C6: =IFERROR(VLOOKUP(B6,Brands!$A:$B,2,FALSE),"") | D6: meta | F6: 2026-08-27 | G6: static | I6: mixed | J6: brand_corporate | K6: national_trust | L6: other | M6: pride | N6: none | O6: none | P6: mass | Q6: no | R6: 1 | T6: https://www.instagram.com/statelifeofficialpakistan/p/Db_cOMoDCos/ | U6: claude | V6: 'Har Khwab Rahe Azaad' - 79 Years of Freedom. Calendar. [img: media/statelifeofficialpakistan/Db_cOMoDCos.jpg]
A7: =IF(B7="","",ROW()-1) | B7: State Life Insurance Corporation of Pakistan | C7: =IFERROR(VLOOKUP(B7,Brands!$A:$B,2,FALSE),"") | D7: meta | F7: 2026-08-27 | G7: video | I7: mixed | J7: brand_corporate | K7: brand_corporate | L7: other | M7: pride | N7: expert_authority | O7: none | P7: sme_corporate | Q7: no | R7: 1 | T7: https://www.instagram.com/vcastonline/reel/Db5AI2Joex3/ | U7: claude | V7: REPOST from @vcastonline. CEO at IAP/PSOA conference: 'Insurance: the quiet driver of growth'. [img: media/statelifeofficialpakistan/Db5AI2Joex3.jpg]
A8: =IF(B8="","",ROW()-1) | B8: State Life Insurance Corporation of Pakistan | C8: =IFERROR(VLOOKUP(B8,Brands!$A:$B,2,FALSE),"") | D8: meta | F8: 2026-08-27 | G8: static | I8: mixed | J8: brand_corporate | K8: national_trust | L8: other | M8: reassurance | N8: claim_statistics | O8: call_centre | P8: mass | Q8: yes | R8: 1 | T8: https://www.instagram.com/statelifeofficialpakistan/p/Db40vJeDIdE/ | U8: claude | V8: E-Kachehri: 745 received -> 744 resolved. Bilingual. Grievance-redress framing, not advertising. [img: media/statelifeofficialpakistan/Db40vJeDIdE.jpg]
A9: =IF(B9="","",ROW()-1) | B9: State Life Insurance Corporation of Pakistan | C9: =IFERROR(VLOOKUP(B9,Brands!$A:$B,2,FALSE),"") | D9: meta | F9: 2026-08-27 | G9: static | I9: mixed | J9: health | K9: protection | L9: other | M9: reassurance | N9: heritage_scale | O9: digital_direct | P9: mass | Q9: no | R9: 1 | T9: https://www.instagram.com/statelifeofficialpakistan/p/DbzJUzCgQRC/ | U9: claude | V9: CAMPAIGN: 'Healthcare planning starts before you ever need care / PLAN AHEAD'. [img: media/statelifeofficialpakistan/DbzJUzCgQRC.jpg]
A10: =IF(B10="","",ROW()-1) | B10: State Life Insurance Corporation of Pakistan | C10: =IFERROR(VLOOKUP(B10,Brands!$A:$B,2,FALSE),"") | D10: meta | F10: 2026-08-27 | G10: static | I10: mixed | J10: individual_life | K10: protection | L10: savings_return | M10: aspiration | N10: heritage_scale | O10: digital_direct | P10: mass | Q10: no | R10: 1 | T10: https://www.instagram.com/statelifeofficialpakistan/p/DbygIFcEQfj/ | U10: claude | V10: CAMPAIGN: 'The best opportunities are easier to seize when you're prepared / PLAN AHEAD'. Skydiving. [img: media/statelifeofficialpakistan/DbygIFcEQfj.jpg]
A11: =IF(B11="","",ROW()-1) | B11: State Life Insurance Corporation of Pakistan | C11: =IFERROR(VLOOKUP(B11,Brands!$A:$B,2,FALSE),"") | D11: meta | F11: 2026-08-27 | G11: static | I11: mixed | J11: child_education | K11: protection | L11: education_marriage | M11: reassurance | N11: heritage_scale | O11: digital_direct | P11: mass | Q11: no | R11: 1 | T11: https://www.instagram.com/statelifeofficialpakistan/p/Dbx2qijjH7a/ | U11: claude | V11: CAMPAIGN: 'Education Planning Starts Years Before the Admission Form / PLAN AHEAD WITH STATE LIFE'. Footer claims 'Pakistan's Largest Life and Health Insurer'. [img: media/statelifeofficialpakistan/Dbx2qijjH7a.jpg]
A12: =IF(B12="","",ROW()-1) | B12: State Life Insurance Corporation of Pakistan | C12: =IFERROR(VLOOKUP(B12,Brands!$A:$B,2,FALSE),"") | D12: meta | F12: 2026-08-27 | G12: static | I12: mixed | J12: brand_corporate | K12: brand_corporate | L12: other | M12: pride | N12: none | O12: none | P12: sme_corporate | Q12: no | R12: 1 | T12: https://www.instagram.com/statelifeofficialpakistan/p/DbfQOFYn5_V/ | U12: claude | V12: CEO with Federal Minister. Grip-and-grin. [img: media/statelifeofficialpakistan/DbfQOFYn5_V.jpg]
A13: =IF(B13="","",ROW()-1) | B13: State Life Insurance Corporation of Pakistan | C13: =IFERROR(VLOOKUP(B13,Brands!$A:$B,2,FALSE),"") | D13: meta | F13: 2026-08-27 | G13: video | I13: mixed | J13: unclear | K13: other | L13: other | M13: reassurance | N13: none | O13: none | P13: mass | Q13: no | R13: 1 | T13: https://www.instagram.com/statelifeofficialpakistan/reel/DbOTNzjlDXw/ | U13: claude | V13: NOT YET CODED - open the full-size file in media/ and code it. [img: media/statelifeofficialpakistan/DbOTNzjlDXw.jpg]
... A145: =IF(B145="","",ROW()-1) | B145: UBL Fund Managers | C145: =IFERROR(VLOOKUP(B145,Brands!$A:$B,2,FALSE),"") | D145: meta | F145: 2026-08-27 | G145: static | I145: mixed | J145: unclear | K145: other | L145: other | M145: reassurance | N145: none | O145: none | P145: mass | Q145: no | R145: 1 | T145: https://www.instagram.com/ublfunds/p/DcLgeH8lLnr/ | U145: claude | V145: NOT YET CODED - open the full-size file in media/ and code it. [img: media/ublfunds/DcLgeH8lLnr.jpg]
A146: =IF(B146="","",ROW()-1) | C146: =IFERROR(VLOOKUP(B146,Brands!$A:$B,2,FALSE),"")
A147: =IF(B147="","",ROW()-1) | C147: =IFERROR(VLOOKUP(B147,Brands!$A:$B,2,FALSE),"")
A148: =IF(B148="","",ROW()-1) | C148: =IFERROR(VLOOKUP(B148,Brands!$A:$B,2,FALSE),"")
A149: =IF(B149="","",ROW()-1) | C149: =IFERROR(VLOOKUP(B149,Brands!$A:$B,2,FALSE),"")
A150: =IF(B150="","",ROW()-1) | C150: =IFERROR(VLOOKUP(B150,Brands!$A:$B,2,FALSE),"")
A151: =IF(B151="","",ROW()-1) | C151: =IFERROR(VLOOKUP(B151,Brands!$A:$B,2,FALSE),"")
A152: =IF(B152="","",ROW()-1) | C152: =IFERROR(VLOOKUP(B152,Brands!$A:$B,2,FALSE),"")
A153: =IF(B153="","",ROW()-1) | C153: =IFERROR(VLOOKUP(B153,Brands!$A:$B,2,FALSE),"")
A154: =IF(B154="","",ROW()-1) | C154: =IFERROR(VLOOKUP(B154,Brands!$A:$B,2,FALSE),"")
A155: =IF(B155="","",ROW()-1) | C155: =IFERROR(VLOOKUP(B155,Brands!$A:$B,2,FALSE),"")
A156: =IF(B156="","",ROW()-1) | C156: =IFERROR(VLOOKUP(B156,Brands!$A:$B,2,FALSE),"")
A157: =IF(B157="","",ROW()-1) | C157: =IFERROR(VLOOKUP(B157,Brands!$A:$B,2,FALSE),"")
... A601: =IF(B601="","",ROW()-1) | C601: =IFERROR(VLOOKUP(B601,Brands!$A:$B,2,FALSE),"")

Sheet README
A1: Competitor communications audit
A2: Category | B2: Life insurance (Pakistan) - SLIC P78118
A3: Collection started | B3: 2026-08-26
A4: Collection window | B4: Sep 2025 - Aug 2026 (owned-channel campaign library has no per-asset dates; date_last_seen = date collected)
A5: Brands in scope | B5: 16
A7: Core category objection | B7: <the single objection ads are coded against, e.g. 'will they actually pay out?'>
A8: Row = concept or asset? | B8: <decide once, apply consistently; note variant_count>
A10: Before coding | B10: Read references/coding-schema.md. Code the same ten ads as a group, reconcile, then split the work.
A11: Every row needs | B11: a source_url. Rows without provenance are dropped at analysis.
A12: Screenshots | B12: <folder path -- ads come down; keep the evidence>
A14: Analyse with | B14: python analyze_audit.py capture.xlsx --out <dir>

Sheet Brands
A1: brand | B1: ring | C1: notes
A2: State Life Insurance Corporation of Pakistan | B2: client | C2: Market leader in life; state-owned. Sovereign backing + tied agency network are the assets competitors cannot copy.
A3: EFU Life Assurance | B3: direct | C3: Largest private life insurer. Heavy bancassurance distribution.
A4: Jubilee Life Insurance | B4: direct | C4: Aga Khan / Habib group. Strong bancassurance and digital presence.
A5: Adamjee Life Assurance | B5: direct | C5: MCB-linked distribution.
A6: IGI Life Insurance | B6: direct | C6: Packages group. Smaller, affluent skew.
A7: Askari Life Assurance | B7: direct | C7: Army Welfare Trust linked - note it also claims an institutional-trust territory.
A8: TPL Life Insurance | B8: direct | C8: Digital-first challenger; check convenience_digital claim.
A9: Pak-Qatar Family Takaful | B9: adjacent | C9: Dedicated family Takaful operator.
A10: Dawood Family Takaful | B10: adjacent | C10: Dedicated family Takaful operator.
A11: EFU Life Window Takaful | B11: adjacent | C11: Search separately from EFU Life - window operations advertise under their own page names.
A12: Jubilee Life Window Takaful | B12: adjacent | C12: Search separately from Jubilee Life.
... A17: UBL Fund Managers | B17: substitute | C17: Retirement and savings funds.

Sheet Codes
A1: channel | B1: format | C1: language | D1: product_line | E1: claim | F1: register | G1: proof_device | H1: cta_channel | I1: audience_signal | J1: yes_no
A2: meta | B2: static | C2: urdu | D2: individual_life | E2: protection | F2: fear | G2: sovereign_guarantee | H2: agent | I2: mass | J2: yes
A3: google_search | B3: carousel | C3: english | D3: group_corporate | E3: savings_return | F3: aspiration | G3: ratings_awards | H3: bank_branch | I3: affluent | J3: no
A4: google_display | B4: video | C4: mixed | D4: takaful | E4: education_marriage | F4: duty | G4: testimonial | H4: digital_direct | I4: women
A5: youtube | B5: long_form | C5: regional | D5: savings_investment | E5: retirement | F5: reassurance | G5: claim_statistics | H5: call_centre | I5: youth
A6: tiktok | B6: print | C6: other | D6: health | E6: faith_compliance | F6: pride | G6: celebrity | H6: retail | I6: diaspora
A7: linkedin | B7: ooh | D7: child_education | E7: national_trust | F7: humour | G7: expert_authority | H7: none | I7: sme_corporate
A8: press | B8: radio | D8: retirement | E8: convenience_digital | G8: heritage_scale | I8: rural
A9: tv | B9: other | D9: brand_corporate | E9: price_affordability | G9: none
A10: radio | D10: unclear | E10: brand_corporate
A11: ooh | E11: other
A12: website
A13: other

Sheet MarketShare
A1: brand | B1: metric | C1: value | D1: period | E1: source | F1: source_url
A2: State Life Insurance Corporation of Pakistan | B2: <e.g. gross written premium share, %>
A3: EFU Life Assurance
A4: Jubilee Life Insurance
A5: Adamjee Life Assurance
A6: IGI Life Insurance
A7: Askari Life Assurance
A8: TPL Life Insurance
A9: Pak-Qatar Family Takaful
A10: Dawood Family Takaful
A11: EFU Life Window Takaful
A12: Jubilee Life Window Takaful
A13: Adamjee Life Window Takaful
A14: Postal Life Insurance
... A19: Every figure needs a citable source. Do not enter a number you cannot attribute.
